{
  "$schema": "https://ui.shadcn.com/schema/registry-item.json",
  "name": "avatar-group",
  "title": "Avatar Group",
  "type": "registry:ui",
  "description": "A tiny pile of people. Blame distribution included.",
  "dependencies": [],
  "registryDependencies": [
    "feral-style"
  ],
  "files": [
    {
      "path": "src/components/ui/avatar-group.tsx",
      "type": "registry:ui",
      "content": "import * as React from \"react\";\nimport { cn } from \"../../lib/cn\";\n\nexport function AvatarGroup({ className, ...props }: React.HTMLAttributes<HTMLDivElement>) {\n  return <div className={cn(\"feral-avatar-group\", className)} {...props} />;\n}\n"
    },
    {
      "path": "src/lib/cn.ts",
      "type": "registry:lib",
      "content": "export function cn(...classes: Array<string | false | null | undefined>) {\n  return classes.filter(Boolean).join(\" \");\n}\n"
    }
  ]
}